simple_account_manager/__init__.py
simple_account_manager/account.py
simple_account_manager/manager.py
simple_account_manager-0.0.6.dist-info/METADATA
simple_account_manager-0.0.6.dist-info/WHEEL
simple_account_manager-0.0.6.dist-info/licenses/LICENSE
simple_account_manager-0.0.6.dist-info/RECORD
