Metadata-Version: 2.3
Name: simple_account_manager
Version: 0.0.6
Summary: A simple Python account manager library
Project-URL: homepage, https://github.com/huangyunict/simple_account_manager
Project-URL: issues, https://github.com/huangyunict/simple_account_manager/issues
Author-email: Yun Huang <huangyunict@gmail.com>
Maintainer-email: Yun Huang <huangyunict@gmail.com>
License-File: LICENSE
Classifier: License :: OSI Approved :: MIT License
Classifier: Operating System :: OS Independent
Classifier: Programming Language :: Python :: 3
Requires-Python: >=3.8
Requires-Dist: cryptography>=43.0.0
